031763fc7f5809847693__mypyc.cpython-311-x86_64-linux-gnu.so
xulbux/__init__.cpython-311-x86_64-linux-gnu.so
xulbux/__init__.py
xulbux/code.cpython-311-x86_64-linux-gnu.so
xulbux/code.py
xulbux/color.cpython-311-x86_64-linux-gnu.so
xulbux/color.py
xulbux/console.cpython-311-x86_64-linux-gnu.so
xulbux/console.py
xulbux/data.cpython-311-x86_64-linux-gnu.so
xulbux/data.py
xulbux/env_path.cpython-311-x86_64-linux-gnu.so
xulbux/env_path.py
xulbux/file.cpython-311-x86_64-linux-gnu.so
xulbux/file.py
xulbux/file_sys.cpython-311-x86_64-linux-gnu.so
xulbux/file_sys.py
xulbux/format_codes.cpython-311-x86_64-linux-gnu.so
xulbux/format_codes.py
xulbux/json.cpython-311-x86_64-linux-gnu.so
xulbux/json.py
xulbux/regex.cpython-311-x86_64-linux-gnu.so
xulbux/regex.py
xulbux/string.cpython-311-x86_64-linux-gnu.so
xulbux/string.py
xulbux/system.cpython-311-x86_64-linux-gnu.so
xulbux/system.py
xulbux/base/consts.cpython-311-x86_64-linux-gnu.so
xulbux/base/consts.py
xulbux/base/decorators.cpython-311-x86_64-linux-gnu.so
xulbux/base/decorators.py
xulbux/base/exceptions.cpython-311-x86_64-linux-gnu.so
xulbux/base/exceptions.py
xulbux/base/types.cpython-311-x86_64-linux-gnu.so
xulbux/base/types.py
xulbux/cli/help.cpython-311-x86_64-linux-gnu.so
xulbux/cli/help.py
xulbux-1.9.5.dist-info/METADATA
xulbux-1.9.5.dist-info/WHEEL
xulbux-1.9.5.dist-info/entry_points.txt
xulbux-1.9.5.dist-info/top_level.txt
xulbux-1.9.5.dist-info/RECORD
xulbux-1.9.5.dist-info/licenses/LICENSE
