Metadata-Version: 2.4
Name: xulbux
Version: 1.9.5
Summary: A Python library to simplify common programming tasks.
Author-email: XulbuX <xulbux.real@gmail.com>
Maintainer-email: XulbuX <xulbux.real@gmail.com>
License-Expression: MIT
Project-URL: Homepage, https://github.com/XulbuX/PythonLibraryXulbuX
Project-URL: Documentation, https://github.com/XulbuX/PythonLibraryXulbuX/wiki
Project-URL: Source Code, https://github.com/XulbuX/PythonLibraryXulbuX/tree/main/src
Project-URL: Changelog, https://github.com/XulbuX/PythonLibraryXulbuX/blob/main/CHANGELOG.md
Project-URL: Bug Reports, https://github.com/XulbuX/PythonLibraryXulbuX/issues
Project-URL: Stats, https://clickpy.clickhouse.com/dashboard/xulbux
Project-URL: License, https://github.com/XulbuX/PythonLibraryXulbuX/blob/main/LICENSE
Keywords: args,arguments,attributes,classes,client,cmd,code,codes,color,commands,console,constants,consts,conversion,convert,data,debug,easier,env,environment,error,file,format,formatting,functions,helper,hex,hexa,hsl,hsla,info,input,json,library,log,logging,methods,nice,operations,path,presets,pretty,printing,properties,python,re,regex,rgb,rgba,string,structures,system,tools,types,utility,warn,warning,xulbux
Classifier: Development Status :: 5 - Production/Stable
Classifier: Programming Language :: Python :: 3.14
Classifier: Programming Language :: Python :: 3.13
Classifier: Programming Language :: Python :: 3.12
Classifier: Programming Language :: Python :: 3.11
Classifier: Programming Language :: Python :: 3.10
Classifier: Operating System :: OS Independent
Classifier: Intended Audience :: Developers
Classifier: Topic :: Software Development :: Libraries :: Python Modules
Requires-Python: >=3.10.0
License-File: LICENSE
Requires-Dist: keyboard>=0.13.5
Requires-Dist: prompt_toolkit>=3.0.41
Requires-Dist: regex>=2023.10.3
Provides-Extra: dev
Requires-Dist: flake8-pyproject>=1.2.3; extra == "dev"
Requires-Dist: flake8>=6.1.0; extra == "dev"
Requires-Dist: pytest>=7.4.2; extra == "dev"
Requires-Dist: toml>=0.10.2; extra == "dev"
Dynamic: license-file
